{
  "version": 1,
  "bpm": 120,
  "offset": 0.0,
  "metadata": {
    "title": "Template Song",
    "artist": "Your Name",
    "charter": "Chart Creator",
    "difficulty": "Normal",
    "level": 5
  },
  "notes": [
    {
      "time": 3.0,
      "pad": 0,
      "type": "normal",
      "comment": "First note - Left Top (W key)"
    },
    {
      "time": 3.5,
      "pad": 3,
      "type": "normal",
      "comment": "Right Top (J key)"
    },
    {
      "time": 4.0,
      "pad": 1,
      "type": "normal",
      "comment": "Left Middle (E key)"
    },
    {
      "time": 4.5,
      "pad": 4,
      "type": "normal",
      "comment": "Right Middle (I key)"
    },
    {
      "time": 5.0,
      "pad": 2,
      "type": "normal",
      "comment": "Left Bottom (F key)"
    },
    {
      "time": 5.5,
      "pad": 5,
      "type": "normal",
      "comment": "Right Bottom (O key)"
    },
    {
      "time": 6.5,
      "pad": 0,
      "type": "normal",
      "comment": "Pattern: Stair climbing left"
    },
    {
      "time": 7.0,
      "pad": 1,
      "type": "normal"
    },
    {
      "time": 7.5,
      "pad": 2,
      "type": "normal"
    },
    {
      "time": 8.5,
      "pad": 3,
      "type": "normal",
      "comment": "Pattern: Stair climbing right"
    },
    {
      "time": 9.0,
      "pad": 4,
      "type": "normal"
    },
    {
      "time": 9.5,
      "pad": 5,
      "type": "normal"
    },
    {
      "time": 11.0,
      "pad": 0,
      "switch_to": 3,
      "type": "switch",
      "comment": "Track switch: Left Top to Right Top"
    },
    {
      "time": 12.0,
      "pad": 3,
      "type": "normal",
      "comment": "Note after switch"
    },
    {
      "time": 13.0,
      "pad": 3,
      "switch_to": 2,
      "type": "switch",
      "comment": "Track switch: Right Top to Left Bottom"
    },
    {
      "time": 14.0,
      "pad": 2,
      "type": "normal"
    },
    {
      "time": 15.0,
      "pad": 1,
      "type": "normal",
      "comment": "Pattern: Alternating sides"
    },
    {
      "time": 15.25,
      "pad": 4,
      "type": "normal"
    },
    {
      "time": 15.5,
      "pad": 1,
      "type": "normal"
    },
    {
      "time": 15.75,
      "pad": 4,
      "type": "normal"
    },
    {
      "time": 16.0,
      "pad": 1,
      "type": "normal"
    },
    {
      "time": 16.25,
      "pad": 4,
      "type": "normal"
    },
    {
      "time": 17.0,
      "pad": 0,
      "type": "normal",
      "comment": "Pattern: Triangle left"
    },
    {
      "time": 17.5,
      "pad": 2,
      "type": "normal"
    },
    {
      "time": 18.0,
      "pad": 1,
      "type": "normal"
    },
    {
      "time": 19.0,
      "pad": 3,
      "type": "normal",
      "comment": "Pattern: Triangle right"
    },
    {
      "time": 19.5,
      "pad": 5,
      "type": "normal"
    },
    {
      "time": 20.0,
      "pad": 4,
      "type": "normal"
    },
    {
      "time": 21.0,
      "pad": 0,
      "type": "normal",
      "comment": "Pattern: Full rotation"
    },
    {
      "time": 21.25,
      "pad": 1,
      "type": "normal"
    },
    {
      "time": 21.5,
      "pad": 2,
      "type": "normal"
    },
    {
      "time": 21.75,
      "pad": 5,
      "type": "normal"
    },
    {
      "time": 22.0,
      "pad": 4,
      "type": "normal"
    },
    {
      "time": 22.25,
      "pad": 3,
      "type": "normal"
    },
    {
      "time": 23.0,
      "pad": 1,
      "switch_to": 4,
      "type": "switch",
      "comment": "Multiple switches in sequence"
    },
    {
      "time": 23.5,
      "pad": 4,
      "switch_to": 2,
      "type": "switch"
    },
    {
      "time": 24.0,
      "pad": 2,
      "switch_to": 3,
      "type": "switch"
    },
    {
      "time": 24.5,
      "pad": 3,
      "type": "normal"
    },
    {
      "time": 26.0,
      "pad": 0,
      "type": "normal",
      "comment": "Ending pattern"
    },
    {
      "time": 26.5,
      "pad": 5,
      "type": "normal"
    },
    {
      "time": 27.0,
      "pad": 1,
      "type": "normal"
    },
    {
      "time": 27.5,
      "pad": 4,
      "type": "normal"
    },
    {
      "time": 28.0,
      "pad": 2,
      "type": "normal"
    },
    {
      "time": 28.5,
      "pad": 3,
      "type": "normal"
    },
    {
      "time": 30.0,
      "pad": 0,
      "type": "normal",
      "comment": "Final note"
    }
  ]
}